Metadata-Version: 2.4
Name: excitingscripts
Version: 1.1.0
Summary: Executable command-line scripts for working with the exciting code.
Author: excitingscripts developers
Maintainer-email: Martin Kuban <kuban@physik.hu-berlin.de>, Mara Voiculescu <voiculem@physik.hu-berlin.de>
License: Copyright 2024 The excitingscripts developers
Project-URL: Source, https://github.com/exciting/exciting
Project-URL: Tutorials, https://exciting-code.org/home/tutorials
Classifier: Programming Language :: Python :: 3.7
Classifier: Operating System :: POSIX :: Linux
Classifier: License :: OSI Approved :: Apache Software License
Requires-Python: >=3.6
License-File: LICENSE
Requires-Dist: numpy>=1.14.5
Requires-Dist: matplotlib>=2.2.0
Requires-Dist: scipy>=1.7.0
Requires-Dist: excitingtools>=1.6.3
Requires-Dist: typing-extensions>=3.7
Requires-Dist: ase>=3.22.1
Dynamic: license-file
